streamlit_tree_select/__init__.py
streamlit_tree_select/frontend/build/asset-manifest.json
streamlit_tree_select/frontend/build/bootstrap.min.css
streamlit_tree_select/frontend/build/index.html
streamlit_tree_select/frontend/build/precache-manifest.e315b19f8d9c953fb3a70cb3aed3f336.js
streamlit_tree_select/frontend/build/react-checkbox-tree.css
streamlit_tree_select/frontend/build/service-worker.js
streamlit_tree_select/frontend/build/font-awesome/css/font-awesome.css
streamlit_tree_select/frontend/build/font-awesome/css/font-awesome.min.css
streamlit_tree_select/frontend/build/font-awesome/fonts/FontAwesome.otf
streamlit_tree_select/frontend/build/font-awesome/fonts/fontawesome-webfont.eot
streamlit_tree_select/frontend/build/font-awesome/fonts/fontawesome-webfont.svg
streamlit_tree_select/frontend/build/font-awesome/fonts/fontawesome-webfont.ttf
streamlit_tree_select/frontend/build/font-awesome/fonts/fontawesome-webfont.woff
streamlit_tree_select/frontend/build/font-awesome/fonts/fontawesome-webfont.woff2
streamlit_tree_select/frontend/build/font-awesome/less/animated.less
streamlit_tree_select/frontend/build/font-awesome/less/bordered-pulled.less
streamlit_tree_select/frontend/build/font-awesome/less/core.less
streamlit_tree_select/frontend/build/font-awesome/less/fixed-width.less
streamlit_tree_select/frontend/build/font-awesome/less/font-awesome.less
streamlit_tree_select/frontend/build/font-awesome/less/icons.less
streamlit_tree_select/frontend/build/font-awesome/less/larger.less
streamlit_tree_select/frontend/build/font-awesome/less/list.less
streamlit_tree_select/frontend/build/font-awesome/less/mixins.less
streamlit_tree_select/frontend/build/font-awesome/less/path.less
streamlit_tree_select/frontend/build/font-awesome/less/rotated-flipped.less
streamlit_tree_select/frontend/build/font-awesome/less/screen-reader.less
streamlit_tree_select/frontend/build/font-awesome/less/stacked.less
streamlit_tree_select/frontend/build/font-awesome/less/variables.less
streamlit_tree_selector-1.1.0.dist-info/licenses/LICENSE
streamlit_tree_selector-1.1.0.dist-info/METADATA
streamlit_tree_selector-1.1.0.dist-info/WHEEL
streamlit_tree_selector-1.1.0.dist-info/top_level.txt
streamlit_tree_selector-1.1.0.dist-info/RECORD
