Metadata-Version: 2.4
Name: streamlit-tree-selector
Version: 1.1.0
Summary: A simple and elegant checkbox tree for Streamlit.
Home-page: https://github.com/BlueGob/streamlit_tree_select
Author: BlueGob
Author-email: 
Requires-Python: >=3.6
License-File: LICENSE
Requires-Dist: streamlit>=0.63
Dynamic: author
Dynamic: description-content-type
Dynamic: home-page
Dynamic: license-file
Dynamic: requires-dist
Dynamic: requires-python
Dynamic: summary
